{
  "schema_version": "1.0",
  "congress": 118,
  "fiscal_years": [
    2024
  ],
  "bill_nature": "supplemental",
  "subcommittees": [
    {
      "division": "A",
      "jurisdiction": "other",
      "title": "Israel Security Supplemental Appropriations Act, 2024",
      "source": {
        "type": "default_rule"
      }
    },
    {
      "division": "B",
      "jurisdiction": "other",
      "title": "Ukraine Security Supplemental Appropriations Act, 2024",
      "source": {
        "type": "default_rule"
      }
    },
    {
      "division": "C",
      "jurisdiction": "other",
      "title": "Indo-Pacific Security Supplemental Appropriations Act, 2024",
      "source": {
        "type": "default_rule"
      }
    },
    {
      "division": "D",
      "jurisdiction": "other",
      "title": "21st Century Peace through Strength Act",
      "source": {
        "type": "default_rule"
      }
    },
    {
      "division": "E",
      "jurisdiction": "other",
      "title": "FEND Off Fentanyl Act",
      "source": {
        "type": "default_rule"
      }
    },
    {
      "division": "F",
      "jurisdiction": "other",
      "title": "Rebuilding Economic Prosperity and Opportunity for Ukrainians Act",
      "source": {
        "type": "default_rule"
      }
    },
    {
      "division": "G",
      "jurisdiction": "other",
      "title": "Other Matters",
      "source": {
        "type": "pattern_match",
        "pattern": "other matters"
      }
    },
    {
      "division": "H",
      "jurisdiction": "other",
      "title": "Protecting Americans from Foreign Adversary Controlled Applications Act",
      "source": {
        "type": "default_rule"
      }
    },
    {
      "division": "I",
      "jurisdiction": "other",
      "title": "Protecting Americans’ Data from Foreign Adversaries Act of 2024",
      "source": {
        "type": "default_rule"
      }
    },
    {
      "division": "J",
      "jurisdiction": "other",
      "title": "SHIP Act",
      "source": {
        "type": "default_rule"
      }
    },
    {
      "division": "K",
      "jurisdiction": "other",
      "title": "Fight Crime Act",
      "source": {
        "type": "default_rule"
      }
    },
    {
      "division": "L",
      "jurisdiction": "other",
      "title": "MAHSA Act",
      "source": {
        "type": "default_rule"
      }
    },
    {
      "division": "M",
      "jurisdiction": "other",
      "title": "Hamas and Other Palestinian Terrorist Groups International Financing Prevention Act",
      "source": {
        "type": "default_rule"
      }
    },
    {
      "division": "N",
      "jurisdiction": "other",
      "title": "No Technology for Terror Act",
      "source": {
        "type": "default_rule"
      }
    },
    {
      "division": "O",
      "jurisdiction": "other",
      "title": "Strengthening Tools to Counter the Use of Human Shields Act",
      "source": {
        "type": "default_rule"
      }
    },
    {
      "division": "P",
      "jurisdiction": "other",
      "title": "Illicit Captagon Trafficking Suppression Act",
      "source": {
        "type": "default_rule"
      }
    },
    {
      "division": "Q",
      "jurisdiction": "other",
      "title": "End Financing for Hamas and State Sponsors of Terrorism Act",
      "source": {
        "type": "default_rule"
      }
    },
    {
      "division": "R",
      "jurisdiction": "other",
      "title": "Holding Iranian Leaders Accountable Act",
      "source": {
        "type": "default_rule"
      }
    },
    {
      "division": "S",
      "jurisdiction": "other",
      "title": "Iran-China Energy Sanctions Act of 2023",
      "source": {
        "type": "default_rule"
      }
    },
    {
      "division": "T",
      "jurisdiction": "budget_process",
      "title": "Budgetary Effects",
      "source": {
        "type": "pattern_match",
        "pattern": "budgetary effects"
      }
    }
  ],
  "provision_timing": [
    {
      "provision_index": 0,
      "timing": "supplemental",
      "available_fy": null,
      "source": {
        "type": "note_text"
      }
    },
    {
      "provision_index": 1,
      "timing": "supplemental",
      "available_fy": null,
      "source": {
        "type": "note_text"
      }
    },
    {
      "provision_index": 2,
      "timing": "supplemental",
      "available_fy": null,
      "source": {
        "type": "note_text"
      }
    },
    {
      "provision_index": 5,
      "timing": "current_year",
      "available_fy": null,
      "source": {
        "type": "default_rule"
      }
    },
    {
      "provision_index": 6,
      "timing": "current_year",
      "available_fy": null,
      "source": {
        "type": "default_rule"
      }
    },
    {
      "provision_index": 7,
      "timing": "supplemental",
      "available_fy": null,
      "source": {
        "type": "note_text"
      }
    },
    {
      "provision_index": 8,
      "timing": "supplemental",
      "available_fy": null,
      "source": {
        "type": "note_text"
      }
    },
    {
      "provision_index": 9,
      "timing": "current_year",
      "available_fy": null,
      "source": {
        "type": "default_rule"
      }
    },
    {
      "provision_index": 10,
      "timing": "current_year",
      "available_fy": null,
      "source": {
        "type": "default_rule"
      }
    },
    {
      "provision_index": 11,
      "timing": "current_year",
      "available_fy": null,
      "source": {
        "type": "default_rule"
      }
    },
    {
      "provision_index": 12,
      "timing": "current_year",
      "available_fy": null,
      "source": {
        "type": "default_rule"
      }
    },
    {
      "provision_index": 16,
      "timing": "current_year",
      "available_fy": null,
      "source": {
        "type": "default_rule"
      }
    },
    {
      "provision_index": 17,
      "timing": "current_year",
      "available_fy": null,
      "source": {
        "type": "default_rule"
      }
    },
    {
      "provision_index": 18,
      "timing": "current_year",
      "available_fy": null,
      "source": {
        "type": "default_rule"
      }
    },
    {
      "provision_index": 19,
      "timing": "supplemental",
      "available_fy": null,
      "source": {
        "type": "note_text"
      }
    },
    {
      "provision_index": 44,
      "timing": "current_year",
      "available_fy": null,
      "source": {
        "type": "default_rule"
      }
    },
    {
      "provision_index": 45,
      "timing": "supplemental",
      "available_fy": null,
      "source": {
        "type": "note_text"
      }
    },
    {
      "provision_index": 46,
      "timing": "current_year",
      "available_fy": null,
      "source": {
        "type": "default_rule"
      }
    },
    {
      "provision_index": 47,
      "timing": "current_year",
      "available_fy": null,
      "source": {
        "type": "default_rule"
      }
    },
    {
      "provision_index": 50,
      "timing": "current_year",
      "available_fy": null,
      "source": {
        "type": "default_rule"
      }
    },
    {
      "provision_index": 51,
      "timing": "current_year",
      "available_fy": null,
      "source": {
        "type": "default_rule"
      }
    },
    {
      "provision_index": 52,
      "timing": "current_year",
      "available_fy": null,
      "source": {
        "type": "default_rule"
      }
    },
    {
      "provision_index": 53,
      "timing": "current_year",
      "available_fy": null,
      "source": {
        "type": "default_rule"
      }
    },
    {
      "provision_index": 54,
      "timing": "supplemental",
      "available_fy": null,
      "source": {
        "type": "note_text"
      }
    },
    {
      "provision_index": 58,
      "timing": "supplemental",
      "available_fy": null,
      "source": {
        "type": "note_text"
      }
    },
    {
      "provision_index": 60,
      "timing": "supplemental",
      "available_fy": null,
      "source": {
        "type": "note_text"
      }
    },
    {
      "provision_index": 72,
      "timing": "current_year",
      "available_fy": null,
      "source": {
        "type": "default_rule"
      }
    },
    {
      "provision_index": 149,
      "timing": "supplemental",
      "available_fy": null,
      "source": {
        "type": "note_text"
      }
    },
    {
      "provision_index": 150,
      "timing": "supplemental",
      "available_fy": null,
      "source": {
        "type": "note_text"
      }
    },
    {
      "provision_index": 205,
      "timing": "supplemental",
      "available_fy": null,
      "source": {
        "type": "note_text"
      }
    },
    {
      "provision_index": 207,
      "timing": "current_year",
      "available_fy": null,
      "source": {
        "type": "default_rule"
      }
    },
    {
      "provision_index": 208,
      "timing": "current_year",
      "available_fy": null,
      "source": {
        "type": "default_rule"
      }
    },
    {
      "provision_index": 209,
      "timing": "current_year",
      "available_fy": null,
      "source": {
        "type": "default_rule"
      }
    },
    {
      "provision_index": 210,
      "timing": "current_year",
      "available_fy": null,
      "source": {
        "type": "default_rule"
      }
    },
    {
      "provision_index": 211,
      "timing": "current_year",
      "available_fy": null,
      "source": {
        "type": "default_rule"
      }
    },
    {
      "provision_index": 212,
      "timing": "current_year",
      "available_fy": null,
      "source": {
        "type": "default_rule"
      }
    },
    {
      "provision_index": 213,
      "timing": "current_year",
      "available_fy": null,
      "source": {
        "type": "default_rule"
      }
    },
    {
      "provision_index": 214,
      "timing": "current_year",
      "available_fy": null,
      "source": {
        "type": "default_rule"
      }
    },
    {
      "provision_index": 265,
      "timing": "current_year",
      "available_fy": null,
      "source": {
        "type": "default_rule"
      }
    },
    {
      "provision_index": 266,
      "timing": "supplemental",
      "available_fy": null,
      "source": {
        "type": "note_text"
      }
    },
    {
      "provision_index": 267,
      "timing": "supplemental",
      "available_fy": null,
      "source": {
        "type": "note_text"
      }
    },
    {
      "provision_index": 268,
      "timing": "supplemental",
      "available_fy": null,
      "source": {
        "type": "note_text"
      }
    },
    {
      "provision_index": 269,
      "timing": "supplemental",
      "available_fy": null,
      "source": {
        "type": "note_text"
      }
    },
    {
      "provision_index": 270,
      "timing": "supplemental",
      "available_fy": null,
      "source": {
        "type": "note_text"
      }
    },
    {
      "provision_index": 271,
      "timing": "supplemental",
      "available_fy": null,
      "source": {
        "type": "note_text"
      }
    },
    {
      "provision_index": 272,
      "timing": "supplemental",
      "available_fy": null,
      "source": {
        "type": "note_text"
      }
    },
    {
      "provision_index": 273,
      "timing": "supplemental",
      "available_fy": null,
      "source": {
        "type": "note_text"
      }
    },
    {
      "provision_index": 274,
      "timing": "supplemental",
      "available_fy": null,
      "source": {
        "type": "note_text"
      }
    },
    {
      "provision_index": 275,
      "timing": "current_year",
      "available_fy": null,
      "source": {
        "type": "default_rule"
      }
    },
    {
      "provision_index": 278,
      "timing": "supplemental",
      "available_fy": null,
      "source": {
        "type": "note_text"
      }
    },
    {
      "provision_index": 279,
      "timing": "supplemental",
      "available_fy": null,
      "source": {
        "type": "note_text"
      }
    },
    {
      "provision_index": 280,
      "timing": "supplemental",
      "available_fy": null,
      "source": {
        "type": "note_text"
      }
    },
    {
      "provision_index": 281,
      "timing": "supplemental",
      "available_fy": null,
      "source": {
        "type": "note_text"
      }
    },
    {
      "provision_index": 282,
      "timing": "supplemental",
      "available_fy": null,
      "source": {
        "type": "note_text"
      }
    },
    {
      "provision_index": 283,
      "timing": "supplemental",
      "available_fy": null,
      "source": {
        "type": "note_text"
      }
    },
    {
      "provision_index": 284,
      "timing": "supplemental",
      "available_fy": null,
      "source": {
        "type": "note_text"
      }
    },
    {
      "provision_index": 285,
      "timing": "supplemental",
      "available_fy": null,
      "source": {
        "type": "note_text"
      }
    },
    {
      "provision_index": 286,
      "timing": "supplemental",
      "available_fy": null,
      "source": {
        "type": "note_text"
      }
    },
    {
      "provision_index": 287,
      "timing": "supplemental",
      "available_fy": null,
      "source": {
        "type": "note_text"
      }
    },
    {
      "provision_index": 288,
      "timing": "supplemental",
      "available_fy": null,
      "source": {
        "type": "note_text"
      }
    },
    {
      "provision_index": 289,
      "timing": "supplemental",
      "available_fy": null,
      "source": {
        "type": "note_text"
      }
    },
    {
      "provision_index": 290,
      "timing": "supplemental",
      "available_fy": null,
      "source": {
        "type": "note_text"
      }
    },
    {
      "provision_index": 291,
      "timing": "current_year",
      "available_fy": null,
      "source": {
        "type": "default_rule"
      }
    },
    {
      "provision_index": 293,
      "timing": "supplemental",
      "available_fy": null,
      "source": {
        "type": "note_text"
      }
    },
    {
      "provision_index": 298,
      "timing": "supplemental",
      "available_fy": null,
      "source": {
        "type": "note_text"
      }
    },
    {
      "provision_index": 299,
      "timing": "supplemental",
      "available_fy": null,
      "source": {
        "type": "note_text"
      }
    },
    {
      "provision_index": 300,
      "timing": "supplemental",
      "available_fy": null,
      "source": {
        "type": "note_text"
      }
    },
    {
      "provision_index": 301,
      "timing": "supplemental",
      "available_fy": null,
      "source": {
        "type": "note_text"
      }
    }
  ],
  "canonical_accounts": [
    {
      "provision_index": 0,
      "canonical_name": "operation and maintenance, defense-wide"
    },
    {
      "provision_index": 1,
      "canonical_name": "procurement of ammunition, army"
    },
    {
      "provision_index": 2,
      "canonical_name": "procurement, defense-wide"
    },
    {
      "provision_index": 3,
      "canonical_name": "procurement, defense-wide"
    },
    {
      "provision_index": 4,
      "canonical_name": "procurement, defense-wide"
    },
    {
      "provision_index": 5,
      "canonical_name": "defense production act purchases"
    },
    {
      "provision_index": 7,
      "canonical_name": "diplomatic programs"
    },
    {
      "provision_index": 8,
      "canonical_name": "office of inspector general"
    },
    {
      "provision_index": 9,
      "canonical_name": "operating expenses"
    },
    {
      "provision_index": 10,
      "canonical_name": "office of inspector general"
    },
    {
      "provision_index": 11,
      "canonical_name": "transition initiatives"
    },
    {
      "provision_index": 12,
      "canonical_name": "economic support fund"
    },
    {
      "provision_index": 13,
      "canonical_name": "economic support fund"
    },
    {
      "provision_index": 14,
      "canonical_name": "economic support fund"
    },
    {
      "provision_index": 15,
      "canonical_name": "economic support fund"
    },
    {
      "provision_index": 16,
      "canonical_name": "assistance for europe, eurasia and central asia"
    },
    {
      "provision_index": 17,
      "canonical_name": "international narcotics control and law enforcement"
    },
    {
      "provision_index": 18,
      "canonical_name": "nonproliferation, anti-terrorism, demining and related programs"
    },
    {
      "provision_index": 19,
      "canonical_name": "foreign military financing program"
    },
    {
      "provision_index": 20,
      "canonical_name": "foreign military financing program"
    },
    {
      "provision_index": 44,
      "canonical_name": "spending reduction account"
    },
    {
      "provision_index": 45,
      "canonical_name": "operation and maintenance, navy"
    },
    {
      "provision_index": 46,
      "canonical_name": "operation and maintenance, defense-wide"
    },
    {
      "provision_index": 47,
      "canonical_name": "shipbuilding and conversion, navy"
    },
    {
      "provision_index": 48,
      "canonical_name": "shipbuilding and conversion, navy"
    },
    {
      "provision_index": 49,
      "canonical_name": "shipbuilding and conversion, navy"
    },
    {
      "provision_index": 50,
      "canonical_name": "other procurement, navy"
    },
    {
      "provision_index": 51,
      "canonical_name": "defense production act purchases"
    },
    {
      "provision_index": 52,
      "canonical_name": "research, development, test and evaluation, navy"
    },
    {
      "provision_index": 54,
      "canonical_name": "military construction, navy and marine corps"
    },
    {
      "provision_index": 58,
      "canonical_name": "foreign military financing program"
    },
    {
      "provision_index": 59,
      "canonical_name": "foreign military financing program"
    },
    {
      "provision_index": 60,
      "canonical_name": "contribution to the international development association"
    },
    {
      "provision_index": 72,
      "canonical_name": "spending reduction account"
    },
    {
      "provision_index": 149,
      "canonical_name": "operations and support"
    },
    {
      "provision_index": 150,
      "canonical_name": "federal assistance"
    },
    {
      "provision_index": 151,
      "canonical_name": "federal assistance"
    },
    {
      "provision_index": 152,
      "canonical_name": "federal assistance"
    },
    {
      "provision_index": 164,
      "canonical_name": "ukraine support fund"
    },
    {
      "provision_index": 205,
      "canonical_name": "diplomatic programs"
    },
    {
      "provision_index": 206,
      "canonical_name": "diplomatic programs"
    },
    {
      "provision_index": 207,
      "canonical_name": "office of inspector general"
    },
    {
      "provision_index": 208,
      "canonical_name": "emergencies in the diplomatic and consular service"
    },
    {
      "provision_index": 209,
      "canonical_name": "office of inspector general"
    },
    {
      "provision_index": 210,
      "canonical_name": "international disaster assistance"
    },
    {
      "provision_index": 211,
      "canonical_name": "migration and refugee assistance"
    },
    {
      "provision_index": 212,
      "canonical_name": "international narcotics control and law enforcement"
    },
    {
      "provision_index": 213,
      "canonical_name": "peacekeeping operations"
    },
    {
      "provision_index": 214,
      "canonical_name": "foreign military financing program"
    },
    {
      "provision_index": 215,
      "canonical_name": "foreign military financing program"
    },
    {
      "provision_index": 216,
      "canonical_name": "foreign military financing program"
    },
    {
      "provision_index": 265,
      "canonical_name": "spending reduction account"
    },
    {
      "provision_index": 266,
      "canonical_name": "military personnel, army"
    },
    {
      "provision_index": 267,
      "canonical_name": "military personnel, marine corps"
    },
    {
      "provision_index": 268,
      "canonical_name": "military personnel, air force"
    },
    {
      "provision_index": 269,
      "canonical_name": "military personnel, space force"
    },
    {
      "provision_index": 270,
      "canonical_name": "operation and maintenance, army"
    },
    {
      "provision_index": 271,
      "canonical_name": "operation and maintenance, navy"
    },
    {
      "provision_index": 272,
      "canonical_name": "operation and maintenance, marine corps"
    },
    {
      "provision_index": 273,
      "canonical_name": "operation and maintenance, air force"
    },
    {
      "provision_index": 274,
      "canonical_name": "operation and maintenance, space force"
    },
    {
      "provision_index": 275,
      "canonical_name": "operation and maintenance, defense-wide"
    },
    {
      "provision_index": 276,
      "canonical_name": "operation and maintenance, defense-wide"
    },
    {
      "provision_index": 278,
      "canonical_name": "missile procurement, army"
    },
    {
      "provision_index": 279,
      "canonical_name": "procurement of ammunition, army"
    },
    {
      "provision_index": 280,
      "canonical_name": "other procurement, army"
    },
    {
      "provision_index": 281,
      "canonical_name": "weapons procurement, navy"
    },
    {
      "provision_index": 282,
      "canonical_name": "other procurement, navy"
    },
    {
      "provision_index": 283,
      "canonical_name": "procurement, marine corps"
    },
    {
      "provision_index": 284,
      "canonical_name": "missile procurement, air force"
    },
    {
      "provision_index": 285,
      "canonical_name": "other procurement, air force"
    },
    {
      "provision_index": 286,
      "canonical_name": "procurement, defense-wide"
    },
    {
      "provision_index": 287,
      "canonical_name": "research, development, test and evaluation, army"
    },
    {
      "provision_index": 288,
      "canonical_name": "research, development, test and evaluation, navy"
    },
    {
      "provision_index": 289,
      "canonical_name": "research, development, test and evaluation, air force"
    },
    {
      "provision_index": 290,
      "canonical_name": "research, development, test and evaluation, defense-wide"
    },
    {
      "provision_index": 291,
      "canonical_name": "office of the inspector general"
    },
    {
      "provision_index": 293,
      "canonical_name": "intelligence community management account"
    },
    {
      "provision_index": 298,
      "canonical_name": "science"
    },
    {
      "provision_index": 299,
      "canonical_name": "defense nuclear nonproliferation"
    },
    {
      "provision_index": 300,
      "canonical_name": "federal salaries and expenses"
    },
    {
      "provision_index": 301,
      "canonical_name": "refugee and entrant assistance"
    }
  ],
  "extraction_sha256": "0589ca94548aba34a69d5e12b20069e8cf62a77fd85c57bb58b47b115ca38b2d"
}